g3projects/__init__.py
g3projects/py.typed
g3projects/logical/__init__.py
g3projects/logical/_logical.py
g3projects/logical/templates/ansic_prg.tpl
g3projects/logical/templates/autogenerated_block.tpl
g3projects/logical/templates/config_txt.tpl
g3projects/logical/templates/main_c.tpl
g3projects/logical/templates/main_c_system.tpl
g3projects/logical/templates/package_pkg_logical.tpl
g3projects/logical/templates/package_pkg_project.tpl
g3projects/logical/templates/package_pkg_system.tpl
g3projects/logical/templates/variables_var.tpl
g3projects/logical/templates/variables_var_system.tpl
g3projects/main/__init__.py
g3projects/main/_main.py
g3projects/physical/__init__.py
g3projects/physical/_physical.py
g3projects/physical/templates/config_pkg.tpl
g3projects/physical/templates/config_sfdomain.tpl
g3projects/physical/templates/cpu_pkg.tpl
g3projects/physical/templates/hardware_hw.tpl
g3projects/physical/templates/iomap_iom.tpl
g3projects/physical/templates/physical_pkg.tpl
g3projects/physical/templates/zone_sw.tpl
g3projects/utils/__init__.py
g3projects/utils/_utils.py
g3projects-0.2.12.dist-info/licenses/LICENCE
g3projects-0.2.12.dist-info/METADATA
g3projects-0.2.12.dist-info/WHEEL
g3projects-0.2.12.dist-info/entry_points.txt
g3projects-0.2.12.dist-info/top_level.txt
g3projects-0.2.12.dist-info/RECORD
